recommender_engine/__init__.py
recommender_engine/recommender.py
recommender_engine/similar_item/__init__.py
recommender_engine/similar_item/find_similar_item.py
recommender_engine/similar_item/preference_space_transform.py
recommender_engine/similar_item/user_match.py
recommender_engine/similarity_measure/__init__.py
recommender_engine/similarity_measure/cosine.py
recommender_engine/similarity_measure/euclidean_distance.py
recommender_engine/similarity_measure/pearson_correlation.py
recommender_engine-0.3.0.dist-info/LICENSE
recommender_engine-0.3.0.dist-info/METADATA
recommender_engine-0.3.0.dist-info/WHEEL
recommender_engine-0.3.0.dist-info/top_level.txt
recommender_engine-0.3.0.dist-info/RECORD
