Metadata-Version: 2.1
Name: recommender-engine
Version: 0.3.0
Summary: A recommendation application using either item-based or user-based approaches
Home-page: https://github.com/tranlyvu/recommender
Author: Tran Ly Vu
Author-email: vutransingapore@gmail.com
Maintainer: Tran Ly Vu <vutransingapore@gmail.com>
Maintainer-email: vutransingapore@gmail.com
License: Apache License 2.0
Download-URL: https://github.com/tranlyvu/recommender/releases
Project-URL: Source, https://github.com/tranlyvu/recommender
Project-URL: Tracker, https://github.com/tranlyvu/recommender/issues
Project-URL: Chat: Gitter, https://gitter.im/recommender/Lobby
Project-URL: CI: Travis, https://travis-ci.org/tranlyvu/recommender
Project-URL: Coverage: coveralls, https://coveralls.io/github/tranlyvu/recommender
Keywords: Recommender,Artificial Intelligence,Data Science
Platform: any
Classifier: Programming Language :: Python :: 2
Classifier: Programming Language :: Python :: 2.7
Classifier: Programming Language :: Python :: 3
Classifier: Programming Language :: Python :: 3.6
Classifier: Programming Language :: Python :: 3.7
Classifier: License :: OSI Approved :: Apache Software License 
Classifier: Operating System :: POSIX
Classifier: Operating System :: POSIX :: Linux
Classifier: Operating System :: Unix
Classifier: Development Status :: 4 - Beta
Classifier: Intended Audience :: Science/Research
Classifier: Intended Audience :: End Users/Desktop
Classifier: Intended Audience :: Developers
Classifier: Natural Language :: English
Classifier: Environment :: Console
Classifier: Topic :: Scientific/Engineering
Classifier: Topic :: Scientific/Engineering :: Artificial Intelligence
Classifier: Topic :: Scientific/Engineering :: Information Analysis
Classifier: Topic :: Education
Classifier: Programming Language :: Python :: Implementation :: CPython
Classifier: Programming Language :: Python :: Implementation :: PyPy
Classifier: Framework :: Pytest
Requires-Python: >=2.7, <4
